movie_selector/__init__.py
movie_selector/main.py
movie_selector-1.0.3.dist-info/LICENSE
movie_selector-1.0.3.dist-info/METADATA
movie_selector-1.0.3.dist-info/WHEEL
movie_selector-1.0.3.dist-info/entry_points.txt
movie_selector-1.0.3.dist-info/top_level.txt
movie_selector-1.0.3.dist-info/RECORD
