Metadata-Version: 2.1
Name: movie-selector
Version: 1.0.3
Summary: A CLI tool for random movie selection
Home-page: https://github.com/mcguirepr89/movie_selector
Author: Patrick McGuire
License: MIT
Classifier: Programming Language :: Python :: 3
License-File: LICENSE
Requires-Dist: colorama
